nion/usim_device/CameraDevice.py
nion/usim_device/CameraSimulator.py
nion/usim_device/DeviceConfiguration.py
nion/usim_device/EELSCameraSimulator.py
nion/usim_device/InstrumentDevice.py
nion/usim_device/Noise.py
nion/usim_device/RonchigramCameraSimulator.py
nion/usim_device/SampleSimulator.py
nion/usim_device/ScanDevice.py
nion/usim_device/__init__.py
nion/usim_device/py.typed
nionswift_plugin/usim/InstrumentPanel.py
nionswift_plugin/usim/__init__.py
nionswift_plugin/usim/manifest.json
nionswift_plugin/usim/test/Camera_test.py
nionswift_plugin/usim/test/InstrumentDevice_test.py
nionswift_plugin/usim/test/Scan_test.py
nionswift_plugin/usim/test/__init__.py
nionswift_usim-5.4.2.dist-info/licenses/LICENSE
nionswift_usim-5.4.2.dist-info/METADATA
nionswift_usim-5.4.2.dist-info/WHEEL
nionswift_usim-5.4.2.dist-info/top_level.txt
nionswift_usim-5.4.2.dist-info/RECORD
