Metadata-Version: 2.4
Name: nionswift-usim
Version: 5.4.2
Summary: A Nion Swift package to simulate a STEM microscope, scanner, and cameras.
Home-page: https://github.com/nion-software/nionswift-usim
Author: Nion Software
Author-email: swift@nion.com
License: GPL-3.0-only
Classifier: Development Status :: 5 - Production/Stable
Classifier: License :: OSI Approved :: GNU General Public License v3 (GPLv3)
Classifier: Programming Language :: Python :: 3.11
Classifier: Programming Language :: Python :: 3.12
Classifier: Programming Language :: Python :: 3.13
Requires-Python: >=3.11
License-File: LICENSE
Requires-Dist: nionswift-instrumentation<24.0,>=23.3
Dynamic: license-file
